jsoneditor/__init__.py
jsoneditor/admin.py
jsoneditor/forms.py
jsoneditor/static/jsoneditor/jsoneditor.map
jsoneditor/static/jsoneditor/jsoneditor.min.css
jsoneditor/static/jsoneditor/jsoneditor.min.js
jsoneditor/static/jsoneditor/img/jsoneditor-icons.svg
jsoneditor/templates/jsoneditor/jsoneditor.html
untether_django_jsoneditor-0.1.0.dist-info/LICENSE
untether_django_jsoneditor-0.1.0.dist-info/METADATA
untether_django_jsoneditor-0.1.0.dist-info/WHEEL
untether_django_jsoneditor-0.1.0.dist-info/top_level.txt
untether_django_jsoneditor-0.1.0.dist-info/RECORD
