Metadata-Version: 2.1
Name: untether-django-jsoneditor
Version: 0.1.0
Summary: Django form widget form JSONField
Home-page: https://github.com/Untether-Tech/django-jsoneditor-widget
Author: Charanjit Singh
Author-email: charanjitdotsingh@gmail.com
License: MIT
Platform: UNKNOWN
